sample/__init__.py
sample/greeting.py
hiworker-0.0.2.dist-info/LICENSE
hiworker-0.0.2.dist-info/METADATA
hiworker-0.0.2.dist-info/WHEEL
hiworker-0.0.2.dist-info/top_level.txt
hiworker-0.0.2.dist-info/RECORD
